polinomio/__init__.py
polinomio/polinomios.py
polinomio-0.0.1.dist-info/METADATA
polinomio-0.0.1.dist-info/WHEEL
polinomio-0.0.1.dist-info/top_level.txt
polinomio-0.0.1.dist-info/RECORD
