Metadata-Version: 2.1
Name: polinomio
Version: 0.0.1
Summary: Librería para trabajar con polinomios
Home-page: https://github.com/antoyneGG
Author: Fabian Antoyne Garcia Gallego
Author-email: fabian.agg@hotmail.com
License: Student
Platform: UNKNOWN
